{"cameraMode":{"drawMode":0,"name":"Shaded","section":"Shading Mode"},"sceneLighting":true,"audioPlay":false,"sceneViewState":{"m_AlwaysRefresh":false,"showFog":true,"showSkybox":true,"showFlares":true,"showImageEffects":true,"showParticleSystems":true,"showVisualEffectGraphs":true,"m_FxEnabled":true},"in2DMode":false,"pivot":{"x":25.95773696899414,"y":-1.450927734375,"z":14.527624130249024},"rotation":{"x":0.09112434834241867,"y":0.5119885802268982,"z":-0.0547335222363472,"w":0.8523882627487183},"size":20.926851272583009,"orthographic":false}